{
  "case_id": "Al30MgSi_far",
  "status": "completed",
  "start_time_utc": "2026-07-19T17:47:34.085846+00:00",
  "command": [
    "pw.x"
  ],
  "git_commit": "85c5ee69115f0025c69c5c7071c51954a9bc3eaa",
  "output_path": "runs/production/Al30MgSi_far/pw.out",
  "job_done": true,
  "scf_converged": true,
  "ionic_converged": true,
  "fatal_error": false,
  "total_energy_ev": -3916.6892268655733,
  "atom_count": 32,
  "scf_iterations": 7,
  "wall_time_seconds": null,
  "final_force_ry_bohr": 0.001455,
  "final_pressure_kbar": -2.44,
  "valid_result": true,
  "returncode": 0,
  "finish_time_utc": "2026-07-20T09:53:13.247452+00:00"
}